phantomsetup/__init__.py
phantomsetup/boundary.py
phantomsetup/box.py
phantomsetup/constants.py
phantomsetup/defaults.py
phantomsetup/disc.py
phantomsetup/eos.py
phantomsetup/geometry.py
phantomsetup/infile.py
phantomsetup/orbits.py
phantomsetup/parameters.py
phantomsetup/particles.py
phantomsetup/phantomsetup.py
phantomsetup/sinks.py
phantomsetup/units.py
phantomsetup-0.0.1.dist-info/LICENSE
phantomsetup-0.0.1.dist-info/METADATA
phantomsetup-0.0.1.dist-info/WHEEL
phantomsetup-0.0.1.dist-info/top_level.txt
phantomsetup-0.0.1.dist-info/RECORD
