Metadata-Version: 2.1
Name: phantomsetup
Version: 0.0.1
Summary: Phantom setup with Python and HDF5
Home-page: http://github.com/dmentipl/phantom-setup
Author: Daniel Mentiplay
License: MIT
Platform: UNKNOWN
Requires-Dist: h5py
Requires-Dist: numpy
Requires-Dist: phantomconfig
Requires-Dist: scipy
Requires-Dist: tomlkit
